ost/ost.py
ost/utilities.py
ost-0.1.dev13.dist-info/LICENSE
ost-0.1.dev13.dist-info/METADATA
ost-0.1.dev13.dist-info/WHEEL
ost-0.1.dev13.dist-info/top_level.txt
ost-0.1.dev13.dist-info/RECORD
