Metadata-Version: 2.1
Name: ost
Version: 0.1.dev13
Summary: OpenSubtitles interface for Python 3
Home-page: http://www.github.com/rlirey/ost
Author: Ryan L. Irey
Author-email: ireyx001@umn.edu
License: Apache 2.0 License
Download-URL: http://www.github.com/rlirey/ost
Platform: UNKNOWN
Classifier: Development Status :: 3 - Alpha
Classifier: Environment :: Console
Classifier: Intended Audience :: End Users/Desktop
Classifier: License :: OSI Approved :: Apache Software License
Classifier: Programming Language :: Python :: 3
Classifier: Topic :: Multimedia
Classifier: Operating System :: Microsoft :: Windows
Classifier: Operating System :: POSIX
Classifier: Operating System :: Unix
Classifier: Operating System :: MacOS
Requires-Dist: requests
